CHANGELOG
LICENSE
MANIFEST.in
README.rst
setup.cfg
setup.py
userdocker/__init__.py
userdocker/parser.py
userdocker/userdocker.py
userdocker.egg-info/PKG-INFO
userdocker.egg-info/SOURCES.txt
userdocker.egg-info/dependency_links.txt
userdocker.egg-info/entry_points.txt
userdocker.egg-info/top_level.txt
userdocker.egg-info/zip-safe
userdocker/config/__init__.py
userdocker/config/default.py
userdocker/helpers/__init__.py
userdocker/helpers/cmd.py
userdocker/helpers/exceptions.py
userdocker/helpers/execute.py
userdocker/helpers/logger.py
userdocker/helpers/nvidia.py
userdocker/helpers/parser.py
userdocker/subcommands/__init__.py
userdocker/subcommands/attach.py
userdocker/subcommands/dockviz.py
userdocker/subcommands/images.py
userdocker/subcommands/ps.py
userdocker/subcommands/pull.py
userdocker/subcommands/run.py
userdocker/subcommands/version.py